.gitignore
Makefile
README.rst
setup.py
deframed/__init__.py
deframed/codec.py
deframed/default.py
deframed/server.py
deframed/util.py
deframed/worker.py
deframed.egg-info/PKG-INFO
deframed.egg-info/SOURCES.txt
deframed.egg-info/dependency_links.txt
deframed.egg-info/not-zip-safe
deframed.egg-info/requires.txt
deframed.egg-info/top_level.txt
deframed/remi/__init__.py
deframed/remi/gui.py
deframed/remi/server.py
deframed/static/main.js
deframed/static/site.css
deframed/templates/layout.mustache
example/hello.py
example/minefield_app.py
example/minefield_app.py.orig
example/minefield_embed.py
example/minefield_res/doubt.png
example/minefield_res/flag.png
example/minefield_res/mine.png