Metadata-Version: 1.2
Name: deframed
Version: 0.2.3
Summary: A minimal web non-framework
Home-page: https://github.com/smurfix/deframed
Author: Matthias Urlichs
Author-email: matthias@urlichs.de
License: GPL3
Keywords: async,web,framework
Platform: UNKNOWN
Classifier: Development Status :: 2 - Pre-Alpha
Classifier: Intended Audience :: Developers
Classifier: Framework :: Trio
Classifier: Programming Language :: Python :: 3.7
Classifier: Programming Language :: Python :: 3.8
Classifier: Programming Language :: Python :: Implementation :: CPython
Classifier: Topic :: Communications :: Telephony
Classifier: Topic :: Software Development :: Testing
Classifier: License :: OSI Approved :: GNU General Public License v3 (GPLv3)
Requires-Python: >=3.7
